dtw.py
dtw-1.2.dist-info/DESCRIPTION.rst
dtw-1.2.dist-info/METADATA
dtw-1.2.dist-info/RECORD
dtw-1.2.dist-info/WHEEL
dtw-1.2.dist-info/metadata.json
dtw-1.2.dist-info/top_level.txt
