Metadata-Version: 2.0
Name: dtw
Version: 1.2
Summary: Python DTW Module
Home-page: https://github.com/pierre-rouanet/dtw
Author: Pierre Rouanet
Author-email: pierre.rouanet@gmail.com
License: GNU GENERAL PUBLIC LICENSE Version 3
Platform: UNKNOWN
Requires-Dist: numpy
